escli_tool/__init__.py
escli_tool/_version.py
escli_tool/cli.py
escli_tool/common.py
escli_tool/config.py
escli_tool/handler.py
escli_tool/registry.py
escli_tool/utils.py
escli_tool/commands/__init__.py
escli_tool/commands/add.py
escli_tool/commands/analysis.py
escli_tool/commands/check.py
escli_tool/commands/create.py
escli_tool/commands/delete.py
escli_tool/commands/login.py
escli_tool/commands/search.py
escli_tool/commands/update.py
escli_tool/data/__init__.py
escli_tool/data/base.py
escli_tool/data/vllm_entry.py
escli_tool/processor/__init__.py
escli_tool/processor/accurcy_processor.py
escli_tool/processor/benchmark_analyst.py
escli_tool/processor/benchmark_processor.py
escli_tool/processor/processor_base.py
escli_tool-0.2.3.dist-info/licenses/LICENSE
escli_tool-0.2.3.dist-info/METADATA
escli_tool-0.2.3.dist-info/WHEEL
escli_tool-0.2.3.dist-info/entry_points.txt
escli_tool-0.2.3.dist-info/top_level.txt
escli_tool-0.2.3.dist-info/RECORD
