Metadata-Version: 2.4
Name: escli_tool
Version: 0.2.3
Summary: elastic command line tool
Home-page: https://github.com/cosdt/elastic-tool
Author: Li Wang
License: Apache 2.0
Project-URL: Homepage, https://github.com/Potabk/elastic-tool
Classifier: Programming Language :: Python :: 3.9
Classifier: Programming Language :: Python :: 3.10
Classifier: Programming Language :: Python :: 3.11
Classifier: Programming Language :: Python :: 3.12
Classifier: License :: OSI Approved :: Apache Software License
Classifier: Intended Audience :: Developers
Classifier: Intended Audience :: Information Technology
Classifier: Intended Audience :: Science/Research
Classifier: Topic :: Scientific/Engineering :: Artificial Intelligence
Classifier: Topic :: Scientific/Engineering :: Information Analysis
Requires-Python: >=3.9
License-File: LICENSE
Requires-Dist: decorator
Requires-Dist: pyyaml
Requires-Dist: scipy
Requires-Dist: setuptools
Requires-Dist: setuptools-scm
Requires-Dist: requests
Requires-Dist: keyring
Requires-Dist: keyrings.alt
Requires-Dist: prettytable
Requires-Dist: matplotlib
Dynamic: author
Dynamic: classifier
Dynamic: description
Dynamic: description-content-type
Dynamic: home-page
Dynamic: license
Dynamic: license-file
Dynamic: project-url
Dynamic: requires-dist
Dynamic: requires-python
Dynamic: summary
